board1/circuit/mux_4x1.v
module mux_4x1(input[3:0] i, input[1:0] s, output F);
    assign F = s[1] ? (s[0] ? i[3] : i[2]) : (s[0] ? i[1] : i[0]);
endmodule

board1/mux_4x1/mux_4x1_tb.v
`timescale 1ns / 1ns
`include "mux_4x1.v"

module mux_4x1_tb;

reg [3:0] i;
reg [1:0] s;
wire F;

mux_4x1 uut(.i(i), .s(s), .F(F));

    initial begin
        $dumpfile("mux_4x1.vcd");
        $dumpvars(0,mux_4x1_tb);


        for(integer j=0; j < 64; j = j+1) begin

            {s,i} = j; #10;

        end

        $finish;
    end

endmodule

board1/mux_4x1/mux_4x1.vcd
$date
	Mon Dec  6 12:30:44 2021
$end
$version
	Icarus Verilog
$end
$timescale
	1ns
$end
$scope module mux_4x1_tb $end
$var wire 1 ! F $end
$var reg 4 " i [3:0] $end
$var reg 2 # s [1:0] $end
$scope module uut $end
$var wire 4 $ i [3:0] $end
$var wire 2 % s [1:0] $end
$var wire 1 ! F $end
$upscope $end
$scope begin $ivl_for_loop0 $end
$var integer 32 & j [31:0] $end
$upscope $end
$upscope $end
$enddefinitions $end
#0
$dumpvars
b0 &
b0 %
b0 $
b0 #
b0 "
0!
$end
#10
1!
b1 "
b1 $
b1 &
#20
0!
b10 "
b10 $
b10 &
#30
1!
b11 "
b11 $
b11 &
#40
0!
b100 "
b100 $
b100 &
#50
1!
b101 "
b101 $
b101 &
#60
0!
b110 "
b110 $
b110 &
#70
1!
b111 "
b111 $
b111 &
#80
0!
b1000 "
b1000 $
b1000 &
#90
1!
b1001 "
b1001 $
b1001 &
#100
0!
b1010 "
b1010 $
b1010 &
#110
1!
b1011 "
b1011 $
b1011 &
#120
0!
b1100 "
b1100 $
b1100 &
#130
1!
b1101 "
b1101 $
b1101 &
#140
0!
b1110 "
b1110 $
b1110 &
#150
1!
b1111 "
b1111 $
b1111 &
#160
0!
b1 #
b1 %
b0 "
b0 $
b10000 &
#170
b1 "
b1 $
b10001 &
#180
1!
b10 "
b10 $
b10010 &
#190
b11 "
b11 $
b10011 &
#200
0!
b100 "
b100 $
b10100 &
#210
b101 "
b101 $
b10101 &
#220
1!
b110 "
b110 $
b10110 &
#230
b111 "
b111 $
b10111 &
#240
0!
b1000 "
b1000 $
b11000 &
#250
b1001 "
b1001 $
b11001 &
#260
1!
b1010 "
b1010 $
b11010 &
#270
b1011 "
b1011 $
b11011 &
#280
0!
b1100 "
b1100 $
b11100 &
#290
b1101 "
b1101 $
b11101 &
#300
1!
b1110 "
b1110 $
b11110 &
#310
b1111 "
b1111 $
b11111 &
#320
0!
b10 #
b10 %
b0 "
b0 $
b100000 &
#330
b1 "
b1 $
b100001 &
#340
b10 "
b10 $
b100010 &
#350
b11 "
b11 $
b100011 &
#360
1!
b100 "
b100 $
b100100 &
#370
b101 "
b101 $
b100101 &
#380
b110 "
b110 $
b100110 &
#390
b111 "
b111 $
b100111 &
#400
0!
b1000 "
b1000 $
b101000 &
#410
b1001 "
b1001 $
b101001 &
#420
b1010 "
b1010 $
b101010 &
#430
b1011 "
b1011 $
b101011 &
#440
1!
b1100 "
b1100 $
b101100 &
#450
b1101 "
b1101 $
b101101 &
#460
b1110 "
b1110 $
b101110 &
#470
b1111 "
b1111 $
b101111 &
#480
0!
b11 #
b11 %
b0 "
b0 $
b110000 &
#490
b1 "
b1 $
b110001 &
#500
b10 "
b10 $
b110010 &
#510
b11 "
b11 $
b110011 &
#520
b100 "
b100 $
b110100 &
#530
b101 "
b101 $
b110101 &
#540
b110 "
b110 $
b110110 &
#550
b111 "
b111 $
b110111 &
#560
1!
b1000 "
b1000 $
b111000 &
#570
b1001 "
b1001 $
b111001 &
#580
b1010 "
b1010 $
b111010 &
#590
b1011 "
b1011 $
b111011 &
#600
b1100 "
b1100 $
b111100 &
#610
b1101 "
b1101 $
b111101 &
#620
b1110 "
b1110 $
b111110 &
#630
b1111 "
b1111 $
b111111 &
#640
b1000000 &
