final/siganfu_machine_gun.v
`timescale 1ms / 100ns

module siganfu_machine_gun (
	input sysclk, // done
	input reboot, // done
	input target_locked, 
	input is_enemy,
	input fire_command,
	input firing_mode, // 0 single, 1 auto
	input overheat_sensor,
	output reg [2:0] current_state,
	output reg criticality_alert,
	output reg fire_trigger
);

    reg [2:0] next_st;

	parameter s0 = 3'b000, s1 = 3'b001, s2 = 3'b010, s3 = 3'b011, s4 = 3'b100, s5 = 3'b101;
	integer number_of_bullets,number_of_magazines;


	always @(posedge sysclk or reboot) begin
		if(reboot) begin
			current_state <= s0;
			number_of_bullets = 25;
			number_of_magazines = 3;
			criticality_alert = 1'b0;
			fire_trigger = 1'b0;
			shooted = 1'b0;
		end else
			current_state <= next_st;
	end

	integer shooted;

	always @(current_state or target_locked or is_enemy or fire_command or fire_command or overheat_sensor or sysclk) begin

		case(current_state)
			s0: 
				begin
					if(is_enemy && target_locked && fire_command) begin
						if (firing_mode)
							next_st = s2;
						else
							next_st = s1;
					end else
						next_st = s0;
				end
			s1:
				begin
					if(overheat_sensor)
						next_st = s4;
					else if(number_of_bullets) begin

						if(fire_command) begin
							if (is_enemy & target_locked & (~shooted)) begin
								number_of_bullets = number_of_bullets - 1;
								fire_trigger = 1'b1; #5 
								fire_trigger = 1'b0;
								shooted = 1;
							end
							next_st = 1;
						end 
						else begin
							shooted = 1'b0;
							next_st = s0; 	
						end
					end else begin
						shooted = 1'b0;
						if (number_of_magazines)
							next_st = s3;
						else
							next_st = s5;
					end
					
				end
			s2:
			begin
				if(overheat_sensor)
					next_st = s4;
				else begin
					// if we have any bullet
					if(number_of_bullets) begin
						if(is_enemy & target_locked & fire_command)begin
							number_of_bullets = number_of_bullets - 1;
							fire_trigger = 1'b1; #5 
							fire_trigger = 1'b0;

							if(number_of_bullets)
								next_st = s2;
							else begin
								if(number_of_magazines)
									next_st = s3;
								else
									next_st = s5;
							end

						end else
							next_st = s0;
					end else begin //if we are out of bullets
							// if we have any magazine
							if(number_of_magazines)
								next_st = s3; // go to RELOAD
							else // if we have no magazine left
								next_st = s5;// go to DOWNFALL
					end
				end
			end
			s3:
			begin

				#40

				number_of_bullets = 25;
				number_of_magazines = number_of_magazines - 1;
				if (!number_of_magazines)
					criticality_alert = 1;
				
				#10

				if(is_enemy && target_locked && fire_command) begin
					if(firing_mode)
						next_st = s2;
					else 
						next_st = s1;
				end else
					next_st = s0;
				
				#0;

			end
			s4:
			begin
				#100

				if(number_of_bullets) begin
					if(is_enemy && target_locked && fire_command) begin
						if(firing_mode)
							next_st = s2;
						else
							next_st = s1;
					end else
						next_st = s0;
				end else begin
					if(number_of_magazines)
						next_st = s3;
					else 
						next_st = s5;
				end

				#0;
			end
			s5:
			begin
				if(reboot)
					next_st = s0;
				else
					next_st = s5;
			end
			default:  next_st = current_state;
		endcase
	end	
endmodule

final/Test Benches/siganfu_machine_gun_single_shooting_test.v
`timescale 1ms / 100ns
`include "siganfu_machine_gun.v"

module siganfu_machine_gun_single_shooting_test;
	reg target_locked = 0,
	fire_command = 0,
	firing_mode = 0,
	overheat_sensor = 0,
	is_enemy = 0,
	sysclk = 0,
	reboot = 0;

	// Outputs
	wire [2:0] current_state;
	wire  criticality_alert;
	wire  fire_trigger;

	siganfu_machine_gun uut(.target_locked(target_locked),
		.fire_command(fire_command),
		.firing_mode(firing_mode),
		.overheat_sensor(overheat_sensor),
		.is_enemy(is_enemy),
		.sysclk(sysclk),
		.reboot(reboot),
		.current_state(current_state),
		.criticality_alert(criticality_alert),
		.fire_trigger(fire_trigger)
		);

	parameter TIME_FOR_25_ROUNDS = 250;
	parameter TIME_FOR_10_ROUNDS = 100;
	parameter TIME_FOR_15_ROUNDS = 150;
	parameter TIME_FOR_RELOAD = 50;
	parameter TIME_FOR_COOLDOWN = 100;
	parameter HALF_CLOCK_CYCLE = 5;
	parameter TEST_WAIT = 30; 
	parameter REBOOT_WAIT = 3;

	initial begin
		$dumpfile("smg.vcd");
		$dumpvars;
		forever begin
			#HALF_CLOCK_CYCLE sysclk=~sysclk;
		end
	end
	integer i;

	initial begin
		// Reboot the system
		reboot = 1;
		is_enemy = 0; target_locked = 0; fire_command = 0; firing_mode = 0; overheat_sensor = 0; // All inputs LOW
		#REBOOT_WAIT;
		reboot = 0;

		is_enemy = 1; target_locked = 1; firing_mode = 0;

		// Test continuous firing of single shots
		for (i = 0; i < 30; i = i + 1) begin
			fire_command = 1;
			#TEST_WAIT;
			fire_command = 0;
			#TEST_WAIT;
		end

		$finish;
	end
endmodule

final/smg.vcd
$date
	Sun Jan  9 23:01:54 2022
$end
$version
	Icarus Verilog
$end
$timescale
	100ns
$end
$scope module siganfu_machine_gun_single_shooting_test $end
$var wire 1 ! fire_trigger $end
$var wire 3 " current_state [2:0] $end
$var wire 1 # criticality_alert $end
$var reg 1 $ fire_command $end
$var reg 1 % firing_mode $end
$var reg 1 & is_enemy $end
$var reg 1 ' overheat_sensor $end
$var reg 1 ( reboot $end
$var reg 1 ) sysclk $end
$var reg 1 * target_locked $end
$var integer 32 + i [31:0] $end
$scope module uut $end
$var wire 1 $ fire_command $end
$var wire 1 % firing_mode $end
$var wire 1 & is_enemy $end
$var wire 1 ' overheat_sensor $end
$var wire 1 ( reboot $end
$var wire 1 ) sysclk $end
$var wire 1 * target_locked $end
$var reg 1 # criticality_alert $end
$var reg 3 , current_state [2:0] $end
$var reg 1 ! fire_trigger $end
$var reg 3 - next_st [2:0] $end
$var integer 32 . number_of_bullets [31:0] $end
$var integer 32 / number_of_magazines [31:0] $end
$var integer 32 0 shooted [31:0] $end
$upscope $end
$upscope $end
$enddefinitions $end
#0
$dumpvars
b0 0
b11 /
b11001 .
b0 -
b0 ,
bx +
0*
0)
1(
0'
0&
0%
0$
0#
b0 "
0!
$end
#30000
b1 -
1$
b0 +
1*
1&
0(
#50000
1!
b11000 .
b1 "
b1 ,
1)
#100000
b1 0
0!
0)
#150000
1)
#200000
0)
#250000
1)
#300000
0)
#330000
b0 -
b0 0
0$
#350000
b0 "
b0 ,
1)
#400000
0)
#450000
1)
#500000
0)
#550000
1)
#600000
0)
#630000
b1 -
1$
b1 +
#650000
1!
b10111 .
b1 "
b1 ,
1)
#700000
b1 0
0!
0)
#750000
1)
#800000
0)
#850000
1)
#900000
0)
#930000
b0 -
b0 0
0$
#950000
b0 "
b0 ,
1)
#1000000
0)
#1050000
1)
#1100000
0)
#1150000
1)
#1200000
0)
#1230000
b1 -
1$
b10 +
#1250000
1!
b10110 .
b1 "
b1 ,
1)
#1300000
b1 0
0!
0)
#1350000
1)
#1400000
0)
#1450000
1)
#1500000
0)
#1530000
b0 -
b0 0
0$
#1550000
b0 "
b0 ,
1)
#1600000
0)
#1650000
1)
#1700000
0)
#1750000
1)
#1800000
0)
#1830000
b1 -
1$
b11 +
#1850000
1!
b10101 .
b1 "
b1 ,
1)
#1900000
b1 0
0!
0)
#1950000
1)
#2000000
0)
#2050000
1)
#2100000
0)
#2130000
b0 -
b0 0
0$
#2150000
b0 "
b0 ,
1)
#2200000
0)
#2250000
1)
#2300000
0)
#2350000
1)
#2400000
0)
#2430000
b1 -
1$
b100 +
#2450000
1!
b10100 .
b1 "
b1 ,
1)
#2500000
b1 0
0!
0)
#2550000
1)
#2600000
0)
#2650000
1)
#2700000
0)
#2730000
b0 -
b0 0
0$
#2750000
b0 "
b0 ,
1)
#2800000
0)
#2850000
1)
#2900000
0)
#2950000
1)
#3000000
0)
#3030000
b1 -
1$
b101 +
#3050000
1!
b10011 .
b1 "
b1 ,
1)
#3100000
b1 0
0!
0)
#3150000
1)
#3200000
0)
#3250000
1)
#3300000
0)
#3330000
b0 -
b0 0
0$
#3350000
b0 "
b0 ,
1)
#3400000
0)
#3450000
1)
#3500000
0)
#3550000
1)
#3600000
0)
#3630000
b1 -
1$
b110 +
#3650000
1!
b10010 .
b1 "
b1 ,
1)
#3700000
b1 0
0!
0)
#3750000
1)
#3800000
0)
#3850000
1)
#3900000
0)
#3930000
b0 -
b0 0
0$
#3950000
b0 "
b0 ,
1)
#4000000
0)
#4050000
1)
#4100000
0)
#4150000
1)
#4200000
0)
#4230000
b1 -
1$
b111 +
#4250000
1!
b10001 .
b1 "
b1 ,
1)
#4300000
b1 0
0!
0)
#4350000
1)
#4400000
0)
#4450000
1)
#4500000
0)
#4530000
b0 -
b0 0
0$
#4550000
b0 "
b0 ,
1)
#4600000
0)
#4650000
1)
#4700000
0)
#4750000
1)
#4800000
0)
#4830000
b1 -
1$
b1000 +
#4850000
1!
b10000 .
b1 "
b1 ,
1)
#4900000
b1 0
0!
0)
#4950000
1)
#5000000
0)
#5050000
1)
#5100000
0)
#5130000
b0 -
b0 0
0$
#5150000
b0 "
b0 ,
1)
#5200000
0)
#5250000
1)
#5300000
0)
#5350000
1)
#5400000
0)
#5430000
b1 -
1$
b1001 +
#5450000
1!
b1111 .
b1 "
b1 ,
1)
#5500000
b1 0
0!
0)
#5550000
1)
#5600000
0)
#5650000
1)
#5700000
0)
#5730000
b0 -
b0 0
0$
#5750000
b0 "
b0 ,
1)
#5800000
0)
#5850000
1)
#5900000
0)
#5950000
1)
#6000000
0)
#6030000
b1 -
1$
b1010 +
#6050000
1!
b1110 .
b1 "
b1 ,
1)
#6100000
b1 0
0!
0)
#6150000
1)
#6200000
0)
#6250000
1)
#6300000
0)
#6330000
b0 -
b0 0
0$
#6350000
b0 "
b0 ,
1)
#6400000
0)
#6450000
1)
#6500000
0)
#6550000
1)
#6600000
0)
#6630000
b1 -
1$
b1011 +
#6650000
1!
b1101 .
b1 "
b1 ,
1)
#6700000
b1 0
0!
0)
#6750000
1)
#6800000
0)
#6850000
1)
#6900000
0)
#6930000
b0 -
b0 0
0$
#6950000
b0 "
b0 ,
1)
#7000000
0)
#7050000
1)
#7100000
0)
#7150000
1)
#7200000
0)
#7230000
b1 -
1$
b1100 +
#7250000
1!
b1100 .
b1 "
b1 ,
1)
#7300000
b1 0
0!
0)
#7350000
1)
#7400000
0)
#7450000
1)
#7500000
0)
#7530000
b0 -
b0 0
0$
#7550000
b0 "
b0 ,
1)
#7600000
0)
#7650000
1)
#7700000
0)
#7750000
1)
#7800000
0)
#7830000
b1 -
1$
b1101 +
#7850000
1!
b1011 .
b1 "
b1 ,
1)
#7900000
b1 0
0!
0)
#7950000
1)
#8000000
0)
#8050000
1)
#8100000
0)
#8130000
b0 -
b0 0
0$
#8150000
b0 "
b0 ,
1)
#8200000
0)
#8250000
1)
#8300000
0)
#8350000
1)
#8400000
0)
#8430000
b1 -
1$
b1110 +
#8450000
1!
b1010 .
b1 "
b1 ,
1)
#8500000
b1 0
0!
0)
#8550000
1)
#8600000
0)
#8650000
1)
#8700000
0)
#8730000
b0 -
b0 0
0$
#8750000
b0 "
b0 ,
1)
#8800000
0)
#8850000
1)
#8900000
0)
#8950000
1)
#9000000
0)
#9030000
b1 -
1$
b1111 +
#9050000
1!
b1001 .
b1 "
b1 ,
1)
#9100000
b1 0
0!
0)
#9150000
1)
#9200000
0)
#9250000
1)
#9300000
0)
#9330000
b0 -
b0 0
0$
#9350000
b0 "
b0 ,
1)
#9400000
0)
#9450000
1)
#9500000
0)
#9550000
1)
#9600000
0)
#9630000
b1 -
1$
b10000 +
#9650000
1!
b1000 .
b1 "
b1 ,
1)
#9700000
b1 0
0!
0)
#9750000
1)
#9800000
0)
#9850000
1)
#9900000
0)
#9930000
b0 -
b0 0
0$
#9950000
b0 "
b0 ,
1)
#10000000
0)
#10050000
1)
#10100000
0)
#10150000
1)
#10200000
0)
#10230000
b1 -
1$
b10001 +
#10250000
1!
b111 .
b1 "
b1 ,
1)
#10300000
b1 0
0!
0)
#10350000
1)
#10400000
0)
#10450000
1)
#10500000
0)
#10530000
b0 -
b0 0
0$
#10550000
b0 "
b0 ,
1)
#10600000
0)
#10650000
1)
#10700000
0)
#10750000
1)
#10800000
0)
#10830000
b1 -
1$
b10010 +
#10850000
1!
b110 .
b1 "
b1 ,
1)
#10900000
b1 0
0!
0)
#10950000
1)
#11000000
0)
#11050000
1)
#11100000
0)
#11130000
b0 -
b0 0
0$
#11150000
b0 "
b0 ,
1)
#11200000
0)
#11250000
1)
#11300000
0)
#11350000
1)
#11400000
0)
#11430000
b1 -
1$
b10011 +
#11450000
1!
b101 .
b1 "
b1 ,
1)
#11500000
b1 0
0!
0)
#11550000
1)
#11600000
0)
#11650000
1)
#11700000
0)
#11730000
b0 -
b0 0
0$
#11750000
b0 "
b0 ,
1)
#11800000
0)
#11850000
1)
#11900000
0)
#11950000
1)
#12000000
0)
#12030000
b1 -
1$
b10100 +
#12050000
1!
b100 .
b1 "
b1 ,
1)
#12100000
b1 0
0!
0)
#12150000
1)
#12200000
0)
#12250000
1)
#12300000
0)
#12330000
b0 -
b0 0
0$
#12350000
b0 "
b0 ,
1)
#12400000
0)
#12450000
1)
#12500000
0)
#12550000
1)
#12600000
0)
#12630000
b1 -
1$
b10101 +
#12650000
1!
b11 .
b1 "
b1 ,
1)
#12700000
b1 0
0!
0)
#12750000
1)
#12800000
0)
#12850000
1)
#12900000
0)
#12930000
b0 -
b0 0
0$
#12950000
b0 "
b0 ,
1)
#13000000
0)
#13050000
1)
#13100000
0)
#13150000
1)
#13200000
0)
#13230000
b1 -
1$
b10110 +
#13250000
1!
b10 .
b1 "
b1 ,
1)
#13300000
b1 0
0!
0)
#13350000
1)
#13400000
0)
#13450000
1)
#13500000
0)
#13530000
b0 -
b0 0
0$
#13550000
b0 "
b0 ,
1)
#13600000
0)
#13650000
1)
#13700000
0)
#13750000
1)
#13800000
0)
#13830000
b1 -
1$
b10111 +
#13850000
1!
b1 .
b1 "
b1 ,
1)
#13900000
b1 0
0!
0)
#13950000
1)
#14000000
0)
#14050000
1)
#14100000
0)
#14130000
b0 -
b0 0
0$
#14150000
b0 "
b0 ,
1)
#14200000
0)
#14250000
1)
#14300000
0)
#14350000
1)
#14400000
0)
#14430000
b1 -
1$
b11000 +
#14450000
1!
b0 .
b1 "
b1 ,
1)
#14500000
b1 0
0!
0)
#14550000
b11 -
b0 0
1)
#14600000
0)
#14650000
b11 "
b11 ,
1)
#14700000
0)
#14730000
0$
#14750000
1)
#14800000
0)
#14850000
1)
#14900000
0)
#14950000
1)
#15000000
0)
#15030000
1$
b11001 +
#15050000
1)
b10 /
b11001 .
#15100000
0)
#15150000
1!
b11000 .
b1 "
b1 ,
1)
b1 -
#15200000
b1 0
0!
0)
#15250000
1)
#15300000
0)
#15330000
b0 -
b0 0
0$
#15350000
b0 "
b0 ,
1)
#15400000
0)
#15450000
1)
#15500000
0)
#15550000
1)
#15600000
0)
#15630000
b1 -
1$
b11010 +
#15650000
1!
b10111 .
b1 "
b1 ,
1)
#15700000
b1 0
0!
0)
#15750000
1)
#15800000
0)
#15850000
1)
#15900000
0)
#15930000
b0 -
b0 0
0$
#15950000
b0 "
b0 ,
1)
#16000000
0)
#16050000
1)
#16100000
0)
#16150000
1)
#16200000
0)
#16230000
b1 -
1$
b11011 +
#16250000
1!
b10110 .
b1 "
b1 ,
1)
#16300000
b1 0
0!
0)
#16350000
1)
#16400000
0)
#16450000
1)
#16500000
0)
#16530000
b0 -
b0 0
0$
#16550000
b0 "
b0 ,
1)
#16600000
0)
#16650000
1)
#16700000
0)
#16750000
1)
#16800000
0)
#16830000
b1 -
1$
b11100 +
#16850000
1!
b10101 .
b1 "
b1 ,
1)
#16900000
b1 0
0!
0)
#16950000
1)
#17000000
0)
#17050000
1)
#17100000
0)
#17130000
b0 -
b0 0
0$
#17150000
b0 "
b0 ,
1)
#17200000
0)
#17250000
1)
#17300000
0)
#17350000
1)
#17400000
0)
#17430000
b1 -
1$
b11101 +
#17450000
1!
b10100 .
b1 "
b1 ,
1)
#17500000
b1 0
0!
0)
#17550000
1)
#17600000
0)
#17650000
1)
#17700000
0)
#17730000
b0 -
b0 0
0$
#17750000
b0 "
b0 ,
1)
#17800000
0)
#17850000
1)
#17900000
0)
#17950000
1)
#18000000
0)
#18030000
b11110 +
